CHANGES.rst
MANIFEST.in
README.rst
setup.py
wimms/__init__.py
wimms/schemas.py
wimms/shardedsql.py
wimms/sql.py
wimms/sqliteschemas.py
wimms.egg-info/PKG-INFO
wimms.egg-info/SOURCES.txt
wimms.egg-info/dependency_links.txt
wimms.egg-info/not-zip-safe
wimms.egg-info/requires.txt
wimms.egg-info/top_level.txt
wimms/tests/__init__.py
wimms/tests/test_shardedsql.py
wimms/tests/test_sql.py