Metadata-Version: 1.1
Name: wimms
Version: 0.3
Summary: Where Is My Mozilla Service ?
Home-page: https://github.com/mozilla-services/wimms
Author: Mozilla Services
Author-email: services-dev@mozilla.org
License: UNKNOWN
Keywords: user database
Platform: UNKNOWN
Classifier: Programming Language :: Python
